role_pattern_nlp/__init__.py
role_pattern_nlp/constants.py
role_pattern_nlp/exceptions.py
role_pattern_nlp/match.py
role_pattern_nlp/mutate.py
role_pattern_nlp/role_pattern.py
role_pattern_nlp/role_pattern_builder.py
role_pattern_nlp/role_pattern_set.py
role_pattern_nlp/role_pattern_vis.py
role_pattern_nlp/util.py
role_pattern_nlp/validate.py
test/__init__.py
test/test_role_pattern.py
test/test_smallest_connected_subgraph.py
role_pattern_nlp-0.2.0.dist-info/LICENSE
role_pattern_nlp-0.2.0.dist-info/METADATA
role_pattern_nlp-0.2.0.dist-info/WHEEL
role_pattern_nlp-0.2.0.dist-info/top_level.txt
role_pattern_nlp-0.2.0.dist-info/RECORD
