Metadata-Version: 2.1
Name: role-pattern-nlp
Version: 0.2.0
Summary: Build and match patterns for semantic role labelling
Home-page: https://github.com/cyclecycle/role-pattern-nlp
Author: Nicholas Morley
Author-email: nick.morley111@gmail.com
License: UNKNOWN
Platform: UNKNOWN
Classifier: Programming Language :: Python :: 3
Classifier: License :: OSI Approved :: MIT License
Classifier: Operating System :: OS Independent
Requires-Dist: atomicwrites (==1.3.0)
Requires-Dist: attrs (==19.1.0)
Requires-Dist: blis (==0.2.4)
Requires-Dist: certifi (==2019.6.16)
Requires-Dist: chardet (==3.0.4)
Requires-Dist: cymem (==2.0.2)
Requires-Dist: decorator (==4.4.0)
Requires-Dist: idna (==2.8)
Requires-Dist: importlib-metadata (==0.18)
Requires-Dist: jsonschema (==3.0.1)
Requires-Dist: more-itertools (==7.0.0)
Requires-Dist: murmurhash (==1.0.2)
Requires-Dist: networkx
Requires-Dist: numpy (==1.17.0)
Requires-Dist: packaging (==19.0)
Requires-Dist: plac (==0.9.6)
Requires-Dist: pluggy (==0.12.0)
Requires-Dist: preshed (==2.0.1)
Requires-Dist: py (==1.8.0)
Requires-Dist: pydot (==1.4.1)
Requires-Dist: pyparsing (==2.4.0)
Requires-Dist: pyrsistent (==0.15.2)
Requires-Dist: pytest (==4.6.3)
Requires-Dist: requests (==2.22.0)
Requires-Dist: six (==1.12.0)
Requires-Dist: spacy
Requires-Dist: spacy-pattern-builder
Requires-Dist: srsly (==0.0.7)
Requires-Dist: thinc (==7.0.8)
Requires-Dist: tqdm (==4.32.2)
Requires-Dist: urllib3 (==1.25.3)
Requires-Dist: visualise-spacy-pattern
Requires-Dist: visualise-spacy-tree
Requires-Dist: wasabi (==0.2.2)
Requires-Dist: wcwidth (==0.1.7)
Requires-Dist: zipp (==0.5.1)
